COPYING.txt
MANIFEST.in
README.txt
setup.py
backends/qt/bitmap.cpp
backends/qt/button.cpp
backends/qt/button.h
backends/qt/calendar.cpp
backends/qt/calendar.h
backends/qt/checkbox.cpp
backends/qt/checkbox.h
backends/qt/combobox.cpp
backends/qt/combobox.h
backends/qt/completer.cpp
backends/qt/data_delegate.cpp
backends/qt/data_model.cpp
backends/qt/dialog.cpp
backends/qt/dialog.h
backends/qt/foldpanel.cpp
backends/qt/foldpanel.h
backends/qt/format.cpp
backends/qt/frame.cpp
backends/qt/frame.h
backends/qt/gdi.cpp
backends/qt/grid.cpp
backends/qt/grid.h
backends/qt/groupbox.cpp
backends/qt/groupbox.h
backends/qt/helper_mac.mm
backends/qt/image.cpp
backends/qt/image.h
backends/qt/label.cpp
backends/qt/label.h
backends/qt/line.cpp
backends/qt/line.h
backends/qt/listview.cpp
backends/qt/listview.h
backends/qt/menu.cpp
backends/qt/menu.h
backends/qt/menubar.cpp
backends/qt/menubar.h
backends/qt/menuitem.cpp
backends/qt/menuitem.h
backends/qt/objects.h
backends/qt/panel.cpp
backends/qt/panel.h
backends/qt/popupwindow.cpp
backends/qt/popupwindow.h
backends/qt/printing.cpp
backends/qt/progress.cpp
backends/qt/progress.h
backends/qt/proxy.h
backends/qt/qt_it.h
backends/qt/radio.cpp
backends/qt/radio.h
backends/qt/ranged.cpp
backends/qt/sceneview.cpp
backends/qt/sceneview.h
backends/qt/scrollview.cpp
backends/qt/scrollview.h
backends/qt/searchfield.cpp
backends/qt/searchfield.h
backends/qt/sizer.cpp
backends/qt/sizer.h
backends/qt/slew.cpp
backends/qt/slew.h
backends/qt/slider.cpp
backends/qt/slider.h
backends/qt/spinfield.cpp
backends/qt/spinfield.h
backends/qt/splitview.cpp
backends/qt/splitview.h
backends/qt/stackview.cpp
backends/qt/stackview.h
backends/qt/statusbar.cpp
backends/qt/statusbar.h
backends/qt/systrayicon.cpp
backends/qt/systrayicon.h
backends/qt/tabview.cpp
backends/qt/tabview.h
backends/qt/tabviewpage.cpp
backends/qt/tabviewpage.h
backends/qt/textfield.cpp
backends/qt/textfield.h
backends/qt/textview.cpp
backends/qt/textview.h
backends/qt/toolbar.cpp
slew.egg-info/PKG-INFO
slew.egg-info/SOURCES.txt
slew.egg-info/dependency_links.txt
slew.egg-info/top_level.txt
slew.egg-info/zip-safe
