Metadata-Version: 1.0
Name: slew
Version: 0.9
Summary: Slew GUI library
Home-page: http://code.google.com/p/slew
Author: Angelo Mottola
Author-email: a.mottola@gmail.com
License: LGPL
Keywords: gui,xml,qt,web
Platform: UNKNOWN
Classifier: Programming Language :: Python
Classifier: Programming Language :: C++
Classifier: Development Status :: 4 - Beta
Classifier: Environment :: MacOS X
Classifier: Environment :: Win32 (MS Windows)
Classifier: Environment :: X11 Applications :: Qt
Classifier: Environment :: Web Environment
Classifier: Intended Audience :: Developers
Classifier: License :: OSI Approved :: GNU Library or Lesser General Public License (LGPL)
Classifier: Operating System :: OS Independent
Classifier: Topic :: Software Development :: Libraries :: Python Modules
Classifier: Topic :: Software Development :: User Interfaces
Classifier: Topic :: Software Development :: Widget Sets
